pixelart_modules-0.1.0.dist-info/METADATA
pixelart_modules-0.1.0.dist-info/WHEEL
pixelart_modules-0.1.0.dist-info/licenses/LICENSE
pixelart_modules/__init__.py
pixelart_modules/pixelart_modules.cpython-39-x86_64-linux-gnu.so
pixelart_modules-0.1.0.dist-info/RECORD
