Metadata-Version: 2.3
Name: pixelart_modules
Version: 0.1.0
Classifier: Programming Language :: Rust
Classifier: Programming Language :: Python :: Implementation :: CPython
Classifier: Programming Language :: Python :: Implementation :: PyPy
Requires-Dist: maturin >=1.7.1
License-File: LICENSE
Requires-Python: >=3.8
